{"@context":"http://iiif.io/api/presentation/3/context.json","id":"https://xn--blaufusstlpel-qmb.de/collection.json","items":[{"id":"https://xn--blaufusstlpel-qmb.de/post/elsa-3-1952/manifest.json","label":{"de":["Elsa Heft 3 1952"]},"thumbnail":[{"format":"image/jpeg","height":414,"id":"https://xn--blaufusstlpel-qmb.de/post/elsa-3-1952/front_hu_ef6755c1a5947184.jpg","type":"Image","width":300},{"format":"image/jpeg","height":7116,"id":"https://static.projektemacher.org/blaufusstoelpel/post/elsa-3-1952/front/full/full/0/default.jpg","service":[{"id":"https://static.projektemacher.org/blaufusstoelpel/post/elsa-3-1952/front","profile":"level0","type":"ImageService2"}],"type":"Image","width":5159}],"type":"Manifest"}],"label":{"de":["Blaufußtölpel"]},"type":"Collection"}